consolidate/__init__.py
consolidate/main.py
consolidate-0.1.dist-info/METADATA
consolidate-0.1.dist-info/WHEEL
consolidate-0.1.dist-info/top_level.txt
consolidate-0.1.dist-info/RECORD
